forum/__init__.py
forum/config.py
forum/config.yml.template
forum/main.py
forum/nodes/__init__.py
forum/nodes/chat_message.py
forum/nodes/install_gpu_enabled_llama_cpp.sh
forum/nodes/llm_node.py
forum/nodes/message_aggregate_node.py
forum/nodes/message_filter_node.py
forum/nodes/message_transform_node.py
forum/nodes/stt_node.py
forum/nodes/telegram_bot_node.py
forum/nodes/tts_node.py
forum/plugin/__init__.py
forum/plugin/node/__init__.py
forum/plugin/node/node.py
forum/plugin/node/node_factory.py
forum/plugin/node/node_manager.py
forum/plugin/plugin_loader.py
forum/plugin/protocol/__init__.py
forum/plugin/protocol/plugin.py
forum/plugin/protocol/plugin_factory.py
forum/plugin/protocol/plugin_module.py
forum/plugin/type/__init__.py
forum/protocol_test.py
forum/topic.py
forum-0.1.1.dist-info/METADATA
forum-0.1.1.dist-info/WHEEL
forum-0.1.1.dist-info/RECORD
