Metadata-Version: 2.1
Name: forum
Version: 0.1.1
Summary: 
Author: Caio D
Author-email: caiobd@protonmail.com
Requires-Python: >=3.9,<4.0
Classifier: Programming Language :: Python :: 3
Classifier: Programming Language :: Python :: 3.9
Classifier: Programming Language :: Python :: 3.10
Classifier: Programming Language :: Python :: 3.11
Requires-Dist: llama-cpp-python (>=0.1.77,<0.2.0)
Requires-Dist: pydantic (>=1.10.7,<2.0.0)
Requires-Dist: pytelegrambotapi (>=4.12.0,<5.0.0)
Requires-Dist: pyyaml (>=6.0,<7.0)
Requires-Dist: requests (>=2.29.0,<3.0.0)
